{
  "box1": 14.56,
  "box2": 22.27,
  "box3": 8.02,
  "box4": 10.06,
  "box5": 10.47,
  "box1_updated_utc": "2026-05-10 04:35 UTC",
  "box2_updated_utc": "2026-05-10 04:35 UTC",
  "box3_updated_utc": "2026-05-10 04:35 UTC",
  "box1_risk": 16.3,
  "box1_risk_updated_utc": "2026-05-10 04:35 UTC",
  "box2_risk": 27.0,
  "box2_risk_updated_utc": "2026-05-10 04:35 UTC",
  "box3_risk": 35.7,
  "box3_risk_updated_utc": "2026-05-10 04:35 UTC",
  "box4_risk": 50.8,
  "box5_risk": 65.6,
  "box4_risk_updated_utc": "2026-05-10 04:35 UTC",
  "box4_updated_utc": "2026-05-10 04:35 UTC",
  "box5_updated_utc": "2026-05-10 04:35 UTC",
  "box5_risk_updated_utc": "2026-05-10 04:35 UTC"
}
