{
  "box1": 6.58,
  "box2": 18.32,
  "box3": 5.98,
  "box4": 6.88,
  "box5": 7.79,
  "box1_updated_utc": "2026-04-02 07:49 UTC",
  "box2_updated_utc": "2026-04-02 07:49 UTC",
  "box3_updated_utc": "2026-04-02 07:49 UTC",
  "box1_risk": 15.6,
  "box1_risk_updated_utc": "2026-04-02 07:49 UTC",
  "box2_risk": 26.7,
  "box2_risk_updated_utc": "2026-04-02 07:49 UTC",
  "box3_risk": 35.5,
  "box3_risk_updated_utc": "2026-04-02 07:49 UTC",
  "box4_risk": 50.6,
  "box5_risk": 65.5,
  "box4_risk_updated_utc": "2026-04-02 07:49 UTC",
  "box4_updated_utc": "2026-04-02 07:49 UTC",
  "box5_updated_utc": "2026-04-02 07:49 UTC",
  "box5_risk_updated_utc": "2026-04-02 07:49 UTC"
}
